mdaux/__init__.py
mdaux/analysis/__init__.py
mdaux/analysis/data_manipulation.py
mdaux/analysis/post_processing.py
mdaux/tests/__init__.py
mdaux/tests/test_postprocessing.py
mdaux/utils/__init__.py
mdaux/utils/helpers.py
mdaux/vizualization/__init__.py
mdaux/vizualization/dpm_animation.py
mdaux/vizualization/general.py
mdaux-0.1.5.dist-info/METADATA
mdaux-0.1.5.dist-info/WHEEL
mdaux-0.1.5.dist-info/top_level.txt
mdaux-0.1.5.dist-info/RECORD
