Metadata-Version: 2.1
Name: mdaux
Version: 0.1.5
Summary: A package for analyzing molecular dynamics simulations.
Author: Marshall R. McCraw
License: MIT
Requires-Dist: cycler >=0.12.1
Requires-Dist: joblib >=1.3.2
Requires-Dist: matplotlib >=3.7.3
Requires-Dist: numpy >=1.24.4
Requires-Dist: pandas >=2.0.3
Requires-Dist: tqdm >=4.66.1
